music_de_limiter/__init__.py
music_de_limiter/base_models.py
music_de_limiter/de_limiter.py
music_de_limiter/load_models.py
music_de_limiter/pretrained/args.json
music_de_limiter/pretrained/weights.pth
music_de_limiter-0.1.1.dist-info/LICENSE
music_de_limiter-0.1.1.dist-info/METADATA
music_de_limiter-0.1.1.dist-info/WHEEL
music_de_limiter-0.1.1.dist-info/top_level.txt
music_de_limiter-0.1.1.dist-info/RECORD
